clients/AWSClient.py
clients/DockerClient.py
clients/EnvdClient.py
clients/GCPClient.py
clients/HttpClient.py
clients/JobClient.py
clients/JobStateMachine.py
clients/SetupClient.py
filesystem/SubstrateFilesystem.py
filesystem/__init__.py
resources/__init__.py
resources/check_gpu.py
substrate/__init__.py
utils/check_update.py
utils/console.py
utils/env.py
utils/supabase.py
utils/utils.py
substrate_ai-0.0.7.dist-info/METADATA
substrate_ai-0.0.7.dist-info/WHEEL
substrate_ai-0.0.7.dist-info/entry_points.txt
substrate_ai-0.0.7.dist-info/top_level.txt
substrate_ai-0.0.7.dist-info/RECORD
