Metadata-Version: 2.1
Name: substrate-ai
Version: 0.0.7
Summary: Substrate AI package
Author-email: SubstrateAI <support@substrateai.com>
Project-URL: Homepage, https://docs.substrateai.com/
Keywords: cloud,gpu,ml,ai
Classifier: License :: OSI Approved :: MIT License
Classifier: Programming Language :: Python
Classifier: Programming Language :: Python :: 3
Requires-Python: >=3.9
Provides-Extra: dev
Requires-Dist: black ; extra == 'dev'
Requires-Dist: bumpver ; extra == 'dev'
Requires-Dist: isort ; extra == 'dev'
Requires-Dist: pip-tools ; extra == 'dev'
Requires-Dist: pytest ; extra == 'dev'
